iutil/__init__.py
iutil/datestr.py
iutil/hashes.py
iutil/pdf_helper.py
iutil/platform_enum.py
iutil-0.1.3.dist-info/LICENSE
iutil-0.1.3.dist-info/METADATA
iutil-0.1.3.dist-info/WHEEL
iutil-0.1.3.dist-info/top_level.txt
iutil-0.1.3.dist-info/RECORD
