Metadata-Version: 2.1
Name: iutil
Version: 0.1.3
Summary: common utils across projects
Home-page: https://github.com/JackonYang/iutil
Author: Jackon Yang
Author-email: i@jackon.me
License: MIT
Platform: UNKNOWN
